{
	"id": "local-dev-environment",
	"name": "Local Development",
	"values": [
		{
			"key": "baseUrl",
			"value": "http://localhost:8081",
			"type": "default",
			"enabled": true
		},
		{
			"key": "email",
			"value": "host@example.com",
			"type": "default",
			"enabled": true
		},
		{
			"key": "session_token",
			"value": "",
			"type": "secret",
			"enabled": true
		},
		{
			"key": "meeting_id",
			"value": "test-meeting",
			"type": "default",
			"enabled": true
		},
		{
			"key": "participant_email",
			"value": "attendee@example.com",
			"type": "default",
			"enabled": true
		},
		{
			"key": "participant_session_token",
			"value": "",
			"type": "secret",
			"enabled": true
		},
		{
			"key": "display_name",
			"value": "Test User",
			"type": "default",
			"enabled": true
		}
	],
	"_postman_variable_scope": "environment"
}
